MANIFEST.in
README.rst
setup.py
GeneWordSearch.egg-info/PKG-INFO
GeneWordSearch.egg-info/SOURCES.txt
GeneWordSearch.egg-info/dependency_links.txt
GeneWordSearch.egg-info/requires.txt
GeneWordSearch.egg-info/top_level.txt
bin/gws
genewordsearch/Classes.py
genewordsearch/DBBuilder.py
genewordsearch/GeneWordSearch.py
genewordsearch/__init__.py
genewordsearch/databases/__init__.py
genewordsearch/databases/ath/geneNotes.p
genewordsearch/databases/ath/totalWordCounts.p
genewordsearch/databases/maize/geneNotes.p
genewordsearch/databases/maize/totalWordCounts.p
webapp/__init__.py
webapp/guniConfig.py
webapp/views.py