Metadata-Version: 1.0
Name: GeneWordSearch
Version: 2.5
Summary: Annotation finder for genes.
Home-page: https://github.com/monprin/geneWordSearch/
Author: Joe Jeffers
Author-email: jeffe174@umn.edu
License: GPLv2
Platform: UNKNOWN
